<mxGraphModel dx="940" dy="431" grid="1" gridSize="10" guides="1" tooltips="1" connect="1" fold="1" page="1" pageScale="1" pageWidth="826" pageHeight="1169" style="default-style2" math="0"><root><mxCell id="0"/><mxCell id="1" parent="0"/><mxCell id="2" value="RESTful&#xa;Server" style="shape=umlLifeline;perimeter=lifelinePerimeter;size=46;strokeColor=#0000FF;strokeWidth=2;fillColor=#99FFFF" parent="1" vertex="1"><mxGeometry x="150" y="20" width="100" height="280" as="geometry"/></mxCell><mxCell id="3" value="Interceptor" style="shape=umlLifeline;perimeter=lifelinePerimeter;size=46;strokeColor=#0000FF;strokeWidth=2;fillColor=#99FFFF" parent="1" vertex="1"><mxGeometry x="280" y="20" width="100" height="280" as="geometry"/></mxCell><mxCell id="4" value="Resource/Plain&#xa;Provider&#xa;Method" style="shape=umlLifeline;perimeter=lifelinePerimeter;size=46;strokeColor=#0000FF;strokeWidth=2;fillColor=#99FFFF" parent="1" vertex="1"><mxGeometry x="400" y="20" width="100" height="280" as="geometry"/></mxCell><mxCell id="7" value="" style="ellipse;shape=startState;fillColor=#000000;strokeColor=#ff0000;" parent="1" vertex="1"><mxGeometry x="70" y="80" width="30" height="30" as="geometry"/></mxCell><mxCell id="8" value="Incoming Request" style="edgeStyle=elbowEdgeStyle;elbow=horizontal;verticalAlign=bottom;endArrow=open;endSize=8;strokeColor=#ff0000;entryX=0.5;entryY=0.3;entryPerimeter=0" parent="1" source="7" edge="1"><mxGeometry x="70" y="80" as="geometry"><mxPoint x="200" y="95" as="targetPoint"/></mxGeometry></mxCell><mxCell id="21" value="Request is handled" style="rounded=1;whiteSpace=wrap" parent="1" vertex="1"><mxGeometry x="390" y="150" width="120" height="30" as="geometry"/></mxCell><mxCell id="22" value="" style="edgeStyle=none;align=left;entryX=0.5;entryY=0.632;entryPerimeter=0;exitX=0.5;exitY=0.632;exitPerimeter=0" parent="1" edge="1"><mxGeometry width="100" height="100" relative="1" as="geometry"><mxPoint x="200" y="140.15999999999997" as="sourcePoint"/><mxPoint x="450" y="140.15999999999997" as="targetPoint"/></mxGeometry></mxCell><mxCell id="24" value="" parent="1" vertex="1"><mxGeometry x="320" y="233" width="20" height="27" as="geometry"/></mxCell><mxCell id="25" value="handleException" style="edgeStyle=elbowEdgeStyle;elbow=vertical;verticalAlign=bottom;endArrow=block;exitX=0.5;exitY=0.478;exitPerimeter=0;align=left" parent="1" target="24" edge="1"><mxGeometry x="221.75" y="233.25" as="geometry"><mxPoint x="200" y="233.39999999999998" as="sourcePoint"/></mxGeometry></mxCell><mxCell id="26" value="return true;" style="edgeStyle=elbowEdgeStyle;elbow=vertical;verticalAlign=bottom;dashed=1;endArrow=open;endSize=8;" parent="1" source="24" edge="1"><mxGeometry x="221.75" y="233.25" as="geometry"><mxPoint x="200" y="260" as="targetPoint"/></mxGeometry></mxCell><mxCell id="27" value="" style="ellipse;shape=endState;fillColor=#000000;strokeColor=#ff0000;align=left" parent="1" vertex="1"><mxGeometry x="70" y="270" width="30" height="30" as="geometry"/></mxCell><mxCell id="28" value="Response" style="edgeStyle=orthogonalEdgeStyle;endArrow=block;dashed=0;dashPattern=1 4;align=left;entryX=1;entryY=0.5;exitX=0.5;exitY=0.954;exitPerimeter=0;endFill=1;strokeWidth=1;strokeColor=#FF0000" parent="1" target="27" edge="1"><mxGeometry x="0.500299820107935" y="-13" width="100" height="100" relative="1" as="geometry"><mxPoint x="200" y="285.05999999999995" as="sourcePoint"/><mxPoint x="650" y="213" as="targetPoint"/><mxPoint x="-8" y="-12" as="offset"/></mxGeometry></mxCell><mxCell id="29" value="" style="ellipse;shape=cloud;whiteSpace=wrap;html=1;" vertex="1" parent="1"><mxGeometry x="175" y="100" width="50" height="30" as="geometry"/></mxCell><mxCell id="30" value="throw exception" style="edgeStyle=elbowEdgeStyle;elbow=vertical;verticalAlign=bottom;dashed=1;endArrow=open;endSize=8;" edge="1" parent="1"><mxGeometry x="351.75" y="173.25" as="geometry"><mxPoint x="200" y="200" as="targetPoint"/><mxPoint x="450" y="200" as="sourcePoint"/></mxGeometry></mxCell></root></mxGraphModel>